kicad2junit/__init__.py
kicad2junit/drc.py
kicad2junit/drc2junit.py
kicad2junit/erc.py
kicad2junit/erc2junit.py
kicad2junit/pro.py
kicad2junit-0.1.5.dist-info/METADATA
kicad2junit-0.1.5.dist-info/WHEEL
kicad2junit-0.1.5.dist-info/entry_points.txt
kicad2junit-0.1.5.dist-info/RECORD
