Metadata-Version: 2.1
Name: kicad2junit
Version: 0.1.5
Summary: Convert KiCad ERC/DRC report to Junit reports
Author: Gustav Palmqvist
Author-email: gustavp@gpa-robotics.com
Requires-Python: >=3.10,<4.0
Classifier: License :: OSI Approved :: MIT License
Classifier: Operating System :: OS Independent
Classifier: Programming Language :: Python :: 3
Classifier: Programming Language :: Python :: 3.10
Classifier: Programming Language :: Python :: 3.11
Classifier: Topic :: Utilities
Requires-Dist: dataclasses-json (>=0.5,<0.6)
Requires-Dist: junit-xml (>=1.9,<2.0)
Requires-Dist: typed-argument-parser (>=1.8.1,<2.0.0)
